pycargoebuild/__init__.py
pycargoebuild/__main__.py
pycargoebuild/cargo.py
pycargoebuild/ebuild.py
pycargoebuild/fetch.py
pycargoebuild/format.py
pycargoebuild/license.py
pycargoebuild-0.15.1.data/data/share/bash-completion/completions/pycargoebuild
pycargoebuild-0.15.1.dist-info/entry_points.txt
pycargoebuild-0.15.1.dist-info/licenses/COPYING
pycargoebuild-0.15.1.dist-info/WHEEL
pycargoebuild-0.15.1.dist-info/METADATA
pycargoebuild-0.15.1.dist-info/RECORD
