Metadata-Version: 2.4
Name: pycargoebuild
Version: 0.15.1
Summary: A generator for Rust/Cargo ebuilds written in Python
Author-email: Michał Górny <mgorny@gentoo.org>
Requires-Python: >=3.10
Classifier: License :: OSI Approved :: GNU General Public License v2 or later (GPLv2+)
License-File: COPYING
Requires-Dist: jinja2
Requires-Dist: license_expression
Requires-Dist: tomli >= 1.2.3; python_version < '3.11'
Requires-Dist: rich ; extra == "pretty-log"
Requires-Dist: pytest ; extra == "test"
Project-URL: Homepage, https://github.com/projg2/pycargoebuild/
Provides-Extra: pretty-log
Provides-Extra: test
